{
  "type": "FeatureCollection",
  "features": [
    {
      "type": "Feature",
      "properties": {
        "name": "Aix-les-Milles"
      },
      "geometry": {
        "type": "Point",
        "coordinates": [
          5.367778,
          43.505556
        ]
      }
    },
    {
      "type": "Feature",
      "properties": {
        "name": "Ajaccio"
      },
      "geometry": {
        "type": "Point",
        "coordinates": [
          8.802778,
          41.923611
        ]
      }
    },
    {
      "type": "Feature",
      "properties": {
        "name": "Alès"
      },
      "geometry": {
        "type": "Point",
        "coordinates": [
          4.092778,
          44.069722
        ]
      }
    },
    {
      "type": "Feature",
      "properties": {
        "name": "Aubenas"
      },
      "geometry": {
        "type": "Point",
        "coordinates": [
          4.372222,
          44.598889
        ]
      }
    },
    {
      "type": "Feature",
      "properties": {
        "name": "Bastia"
      },
      "geometry": {
        "type": "Point",
        "coordinates": [
          9.483611,
          42.550833
        ]
      }
    },
    {
      "type": "Feature",
      "properties": {
        "name": "Béziers"
      },
      "geometry": {
        "type": "Point",
        "coordinates": [
          3.353056,
          43.323889
        ]
      }
    },
    {
      "type": "Feature",
      "properties": {
        "name": "Bordeaux-Mérignac"
      },
      "geometry": {
        "type": "Point",
        "coordinates": [
          -0.715278,
          44.828333
        ]
      }
    },
    {
      "type": "Feature",
      "properties": {
        "name": "Cahors"
      },
      "geometry": {
        "type": "Point",
        "coordinates": [
          1.475278,
          44.351389
        ]
      }
    },
    {
      "type": "Feature",
      "properties": {
        "name": "Calvi"
      },
      "geometry": {
        "type": "Point",
        "coordinates": [
          8.793056,
          42.530556
        ]
      }
    },
    {
      "type": "Feature",
      "properties": {
        "name": "Cannes-Mandelieu"
      },
      "geometry": {
        "type": "Point",
        "coordinates": [
          6.953056,
          43.542222
        ]
      }
    },
    {
      "type": "Feature",
      "properties": {
        "name": "Carcassonne"
      },
      "geometry": {
        "type": "Point",
        "coordinates": [
          2.306389,
          43.216389
        ]
      }
    },
    {
      "type": "Feature",
      "properties": {
        "name": "Figari"
      },
      "geometry": {
        "type": "Point",
        "coordinates": [
          9.097778,
          41.500833
        ]
      }
    },
    {
      "type": "Feature",
      "properties": {
        "name": "Hyères"
      },
      "geometry": {
        "type": "Point",
        "coordinates": [
          6.146389,
          43.097222
        ]
      }
    },
    {
      "type": "Feature",
      "properties": {
        "name": "Le Luc"
      },
      "geometry": {
        "type": "Point",
        "coordinates": [
          6.387222,
          43.384722
        ]
      }
    },
    {
      "type": "Feature",
      "properties": {
        "name": "Limoges"
      },
      "geometry": {
        "type": "Point",
        "coordinates": [
          1.179722,
          45.862778
        ]
      }
    },
    {
      "type": "Feature",
      "properties": {
        "name": "Marseille-Provence"
      },
      "geometry": {
        "type": "Point",
        "coordinates": [
          5.221389,
          43.438889
        ]
      }
    },
    {
      "type": "Feature",
      "properties": {
        "name": "Nîmes-Garons"
      },
      "geometry": {
        "type": "Point",
        "coordinates": [
          4.416389,
          43.757778
        ]
      }
    },
    {
      "type": "Feature",
      "properties": {
        "name": "Perpignan"
      },
      "geometry": {
        "type": "Point",
        "coordinates": [
          2.870556,
          42.740833
        ]
      }
    },
    {
      "type": "Feature",
      "properties": {
        "name": "Saint-Pierre (La Réunion)"
      },
      "geometry": {
        "type": "Point",
        "coordinates": [
          55.423333,
          -21.320556
        ]
      }
    },
    {
      "type": "Feature",
      "properties": {
        "name": "Solenzara"
      },
      "geometry": {
        "type": "Point",
        "coordinates": [
          9.406111,
          41.924444
        ]
      }
    },
    {
      "type": "Feature",
      "properties": {
        "name": "Valence-Chabeuil"
      },
      "geometry": {
        "type": "Point",
        "coordinates": [
          4.969722,
          44.921389
        ]
      }
    },
    {
      "type": "Feature",
      "properties": {
        "name": "Vannes-Meucon"
      },
      "geometry": {
        "type": "Point",
        "coordinates": [
          -2.718056,
          47.723333
        ]
      }
    },
    {
      "type": "Feature",
      "properties": {
        "name": "Mont-de-Marsan BA118"
      },
      "geometry": {
        "type": "Point",
        "coordinates": [
          -0.5075,
          43.9117
        ]
      }
    },
    {
      "type": "Feature",
      "properties": {
        "name": "Pau-Pyrénées"
      },
      "geometry": {
        "type": "Point",
        "coordinates": [
          -0.418611,
          43.38
        ]
      }
    },
    {
      "type": "Feature",
      "properties": {
        "name": "Niort-Marais Poitevin"
      },
      "geometry": {
        "type": "Point",
        "coordinates": [
          -0.402778,
          46.311389
        ]
      }
    }
  ]
}